<manifest identifier="astro-course" version="1.2">
  <metadata>
    <schema>ADL SCORM</schema>
    <schemaversion>1.2</schemaversion>
  </metadata>
  <organizations default="default-org">
    <organization identifier="default-org">
      <title>Curso SCORM</title>
      <item identifier="item-index" identifierref="resource-index">
        <title>Inicio</title>
      </item>
      <item identifier="item-sistema_archivos" identifierref="resource-sistema_archivos">
        <title>Sistema de Archivos</title>
      </item>
      <item identifier="item-xml" identifierref="resource-xml">
        <title>XML</title>
      </item>
      <item identifier="item-pytest" identifierref="resource-pytest">
        <title>Pytest</title>
      </item>
    </organization>
  </organizations>
  <resources>
    <resource identifier="resource-index" type="webcontent" href="index.html">
      <file href="index.html" />
      <file href="_astro/index.CWvMdO6T.css" />
    </resource>
    <resource identifier="resource-sistema_archivos" type="webcontent" href="sistema_archivos/index.html">
      <file href="sistema_archivos/index.html" />
      <file href="/_astro/index.CWvMdO6T.css" />
      <file href="/sistema_archivo.mp4" />
    </resource>
    <resource identifier="resource-xml" type="webcontent" href="xml/index.html">
      <file href="xml/index.html" />
      <file href="_astro/index.CWvMdO6T.css" />
      <file href="xml.mp4" />
    </resource>
    <resource identifier="resource-pytest" type="webcontent" href="pytest/index.html">
      <file href="pytest/index.html" />
      <file href="_astro/index.CWvMdO6T.css" />
      <file href="pytest.mp4" />
    </resource>
    <resource identifier="resource-apiwrapper" type="webcontent" href="APIWrapper.js">
      <file href="APIWrapper.js" />
    </resource>
    <resource identifier="resource-favicon" type="webcontent" href="favicon.svg">
      <file href="favicon.svg" />
    </resource>
  </resources>
</manifest>
